LICENSE
MANIFEST.in
README.md
setup.cfg
setup.py
django_irs_filings.egg-info/PKG-INFO
django_irs_filings.egg-info/SOURCES.txt
django_irs_filings.egg-info/dependency_links.txt
django_irs_filings.egg-info/requires.txt
django_irs_filings.egg-info/top_level.txt
irs/__init__.py
irs/admin.py
irs/models.py
irs/management/.DS_Store
irs/management/__init__.py
irs/management/__pycache__/__init__.cpython-34.pyc
irs/management/commands/.DS_Store
irs/management/commands/__init__.py
irs/management/commands/downloadIRS.py
irs/management/commands/loadIRS.py
irs/management/commands/updateIRS.py
irs/management/commands/__pycache__/__init__.cpython-34.pyc
irs/management/commands/__pycache__/loadIRS.cpython-34.pyc
irs/mappings/F8872.csv
irs/mappings/sa.csv
irs/mappings/sb.csv
irs/tests/TestDataFile.txt
irs/tests/__init__.py
irs/tests/tests.py
irs/tests/__pycache__/__init__.cpython-34.pyc
irs/tests/__pycache__/tests.cpython-34.pyc