Metadata-Version: 1.1
Name: django-irs-filings
Version: 0.1.6
Summary: A Django app to download IRS 527 filings and     load them into a database
Home-page: https://github.com/sahilchinoy/django-irs
Author: Sahil Chinoy
Author-email: sahil.chinoy@gmail.com
License: MIT
Platform: UNKNOWN
Classifier: Environment :: Web Environment
Classifier: Framework :: Django
Classifier: Intended Audience :: Developers
Classifier: Operating System :: OS Independent
Classifier: Programming Language :: Python
Classifier: Programming Language :: Python :: 2.7
Classifier: Programming Language :: Python :: 3.3
Classifier: Programming Language :: Python :: 3.4
